AuklandCompsci220IntroductionToAlgorithmsDataStructuresFormalLanguages4e/README.md
AuklandCompsci220IntroductionToAlgorithmsDataStructuresFormalLanguages4e/__init__.py
AuklandCompsci220IntroductionToAlgorithmsDataStructuresFormalLanguages4e/__main__.py
AuklandCompsci220IntroductionToAlgorithmsDataStructuresFormalLanguages4e/file.pdf
AuklandCompsci220IntroductionToAlgorithmsDataStructuresFormalLanguages4e/index.html
aukland_compsci_220_introduction_to_algorithms_data_structures_formal_languages_4e-2024.3.1.0.dist-info/METADATA
aukland_compsci_220_introduction_to_algorithms_data_structures_formal_languages_4e-2024.3.1.0.dist-info/WHEEL
aukland_compsci_220_introduction_to_algorithms_data_structures_formal_languages_4e-2024.3.1.0.dist-info/entry_points.txt
aukland_compsci_220_introduction_to_algorithms_data_structures_formal_languages_4e-2024.3.1.0.dist-info/top_level.txt
aukland_compsci_220_introduction_to_algorithms_data_structures_formal_languages_4e-2024.3.1.0.dist-info/RECORD
